flowfish/__init__.py
flowfish/__main__.py
flowfish/builtins.py
flowfish/code.py
flowfish/conf.py
flowfish/error.py
flowfish/exec.py
flowfish/flow.py
flowfish/flux.py
flowfish/func.py
flowfish/graph.py
flowfish/link.py
flowfish/locks.py
flowfish/logger.py
flowfish/node.py
flowfish/scope.py
flowfish/tools.py
flowfish/utils.py
flowfish-1.0.2.dist-info/LICENSE
flowfish-1.0.2.dist-info/METADATA
flowfish-1.0.2.dist-info/WHEEL
flowfish-1.0.2.dist-info/entry_points.txt
flowfish-1.0.2.dist-info/top_level.txt
flowfish-1.0.2.dist-info/zip-safe
flowfish-1.0.2.dist-info/RECORD
