Metadata-Version: 2.1
Name: flowfish
Version: 1.0.2
Summary: Yet another pythonic workflow engine
Home-page: https://github.com/exdatic/flowfish
Author: André Kischkel
Author-email: andre@exdatis.ai
License: MIT
Classifier: Development Status :: 5 - Production/Stable
Classifier: Environment :: Console
Classifier: Intended Audience :: Developers
Classifier: Intended Audience :: Science/Research
Classifier: License :: OSI Approved :: MIT License
Classifier: Operating System :: POSIX :: Linux
Classifier: Operating System :: MacOS :: MacOS X
Classifier: Operating System :: Microsoft :: Windows
Classifier: Programming Language :: Python :: 3.7
Classifier: Programming Language :: Python :: 3.8
Classifier: Programming Language :: Python :: 3.9
Classifier: Programming Language :: Python :: 3.10
Classifier: Topic :: Scientific/Engineering
Requires-Python: >=3.7
License-File: LICENSE
Requires-Dist: cloudpickle
Requires-Dist: filelock (>2.0)
Requires-Dist: graphviz (>=0.6)
Requires-Dist: loguru
Requires-Dist: murmurhash
Requires-Dist: simpleeval (>=0.9.2)
Requires-Dist: tqdm
Provides-Extra: all
Requires-Dist: uvloop ; extra == 'all'
Provides-Extra: test
Requires-Dist: flake8 ; extra == 'test'
Requires-Dist: pydantic ; extra == 'test'
Requires-Dist: pytest ; extra == 'test'
Requires-Dist: pytest-asyncio ; extra == 'test'
Requires-Dist: uvloop ; extra == 'test'
